{
  "type": "daily",
  "id": "26-02-08",
  "title": "Sunday, Feb 8",
  "dateRange": "February 8, 2026",
  "date": "2026-02-08",
  "generatedAt": "2026-02-13T12:26:16.651Z",
  "highlights": [
    {
      "title": "Google Home is addressing some of its oldest shortcomings – what do you want next?",
      "link": "https://9to5google.com/2026/02/08/google-home-is-addressing-some-of-its-oldest-shortcomings-what-do-you-want-next/",
      "description": "The Google Home experience brings a lot to the table, but it’s also infamously overlooked some features that have taken years to address. As more updates continue to improve on what Google Home can do, what do you want to see next?\nmore…",
      "published": "2026-02-08T17:00:00.000Z",
      "source": "9to5Google",
      "sourceKey": "9to5google",
      "priority": 2,
      "image": "https://9to5google.com/wp-content/uploads/sites/4/2025/09/Google-Home-redesign-Ask.jpg?quality=82&#038;strip=all&#038;w=1600",
      "relevanceScore": 4,
      "matchedKeywords": [
        "google"
      ],
      "category": null
    }
  ],
  "byCategory": {},
  "totalArticles": 1
}